kscope/__init__.py
kscope/hooks.py
kscope/kaleidoscope_sdk.py
kscope/utils.py
kscope-0.11.0.dist-info/LICENSE
kscope-0.11.0.dist-info/METADATA
kscope-0.11.0.dist-info/WHEEL
kscope-0.11.0.dist-info/top_level.txt
kscope-0.11.0.dist-info/RECORD
