Metadata-Version: 2.1
Name: kscope
Version: 0.11.0
Summary: A user toolkit for analyzing and interfacing with Large Language Models (LLMs)
Home-page: https://github.com/VectorInstitute/kaleidoscope-sdk
Author: ['Vector AI Engineering']
Author-email: ai_engineering@vectorinstitute.ai
License: MIT
Keywords: python nlp machine-learning deep-learning distributed-computing neural-networks tensor llm
Classifier: Development Status :: 3 - Alpha
Classifier: Intended Audience :: Science/Research
Classifier: Intended Audience :: Developers
Classifier: License :: OSI Approved :: MIT License
Classifier: Operating System :: POSIX :: Linux
Classifier: Programming Language :: Python :: 3.8
Classifier: Programming Language :: Python :: 3.9
Classifier: Programming Language :: Python :: 3.10
Classifier: Programming Language :: Python :: 3.11
Classifier: Programming Language :: Python :: 3.12
License-File: LICENSE
Requires-Dist: certifi ==2024.7.4
Requires-Dist: charset-normalizer ==3.3.2
Requires-Dist: cloudpickle ==3.0.0
Requires-Dist: filelock ==3.15.4
Requires-Dist: fsspec ==2024.6.1
Requires-Dist: idna ==3.7
Requires-Dist: Jinja2 ==3.1.4
Requires-Dist: MarkupSafe ==2.1.5
Requires-Dist: mpmath ==1.3.0
Requires-Dist: networkx ==3.3
Requires-Dist: numpy ==2.0.0
Requires-Dist: nvidia-cublas-cu12 ==12.1.3.1
Requires-Dist: nvidia-cuda-cupti-cu12 ==12.1.105
Requires-Dist: nvidia-cuda-nvrtc-cu12 ==12.1.105
Requires-Dist: nvidia-cuda-runtime-cu12 ==12.1.105
Requires-Dist: nvidia-cudnn-cu12 ==8.9.2.26
Requires-Dist: nvidia-cufft-cu12 ==11.0.2.54
Requires-Dist: nvidia-curand-cu12 ==10.3.2.106
Requires-Dist: nvidia-cusolver-cu12 ==11.4.5.107
Requires-Dist: nvidia-cusparse-cu12 ==12.1.0.106
Requires-Dist: nvidia-nccl-cu12 ==2.20.5
Requires-Dist: nvidia-nvjitlink-cu12 ==12.5.82
Requires-Dist: nvidia-nvtx-cu12 ==12.1.105
Requires-Dist: requests ==2.32.3
Requires-Dist: sympy ==1.13.0
Requires-Dist: torch ==2.3.1
Requires-Dist: triton ==2.3.1
Requires-Dist: typing-extensions ==4.12.2
Requires-Dist: urllib3 ==2.2.2
